Workbook

Sheet Synthèse
B2: AT225 — VALORISATION 100% DES TITRES
B3: Vente à très court terme — Synthèse exécutive
B5: Société : | C5: ASSISTANCE TECHNIQUE 225 (AT225)
B6: Adresse : | C6: BP 250 Grand Bassam — Côte d'Ivoire
B7: NCC : | C7: 2007015R | D7: Devise : | E7: XOF (Franc CFA)
B8: Date de valorisation : | C8: 5 mai 2026 | D8: Taux EUR/XOF : | E8: 655.957
A10: CHIFFRES CLÉS (CA RÉEL — facturation)
B11: Indicateur | C11: 2024 | D11: 2025 | E11: 2026 YTD (au 04/05) | F11: 2026 Budget
B12: Chiffre d'affaires (M XOF) | C12: 522.5 | D12: 752.5 | E12: 367.1 | F12: 1710
B13: Chiffre d'affaires (k EUR) | C13: =C12*1000/$E$8 -> 796.54612 | D13: =D12*1000/$E$8 -> 1147.1789 | E13: =E12*1000/$E$8 -> 559.64034 | F13: =F12*1000/$E$8 -> 2606.8782
B14: Croissance annuelle | D14: =D12/C12-1 -> 0.44019139 | F14: =F12/D12-1 -> 1.2724252
B15: Nombre de factures | C15: 236 | D15: 266 | E15: 171
A17: FOURCHETTE DE VALORISATION — 100% DES TITRES
B18: Méthode | C18: Bas (M XOF) | D18: Central (M XOF) | E18: Haut (M XOF) | F18: Central (k EUR) | G18: Pondération
B19: DCF (taux d'actualisation 22%) | C19: =DCF!C40 -> 950.44288 | D19: =DCF!D40 -> 1267.2572 | E19: =DCF!E40 -> 1584.0715 | F19: =D19*1000/$E$8 -> 1931.9211 | G19: 0.3
B20: Multiple d'EBITDA normalisé | C20: =Multiples!C20 -> 309.27124 | D20: =Multiples!D20 -> 754.30858 | E20: =Multiples!E20 -> 1312.2137 | F20: =D20*1000/$E$8 -> 1149.936 | G20: 0.4
B21: Multiple de chiffre d'affaires | C21: =Multiples!C29 -> 158.78083 | D21: =Multiples!D29 -> 321.64864 | E21: =Multiples!E29 -> 522.13905 | F21: =D21*1000/$E$8 -> 490.35019 | G21: 0.2
B22: Méthode patrimoniale (ANR) | C22: =Patrimoniale!C20 -> 34.0164 | D22: =Patrimoniale!D20 -> 56.694 | E22: =Patrimoniale!E20 -> 79.3716 | F22: =D22*1000/$E$8 -> 86.429446 | G22: 0.1
B24: VALORISATION CENTRALE PONDÉRÉE | C24: =SUMPRODUCT(C19:C22,G19:G22) -> 443.99917 | D24: =SUMPRODUCT(D19:D22,G19:G22) -> 751.89971 | E24: =SUMPRODUCT(E19:E22,G19:G22) -> 1112.4719 | F24: =D24*1000/$E$8 -> 1146.2637 | G24: =SUM(G19:G22) -> 1
B26: Décote vente à très court terme (liquidité / urgence) | C26: -0.3 | D26: -0.2 | E26: -0.1
B27: VALEUR D'ÉQUITÉ ATTENDUE (vente rapide 100%) | C27: =C24*(1+C26) -> 310.79942 | D27: =D24*(1+D26) -> 601.51977 | E27: =E24*(1+E26) -> 1001.2247 | F27: =D27*1000/$E$8 -> 917.01098
A29: RECOMMANDATION DE PRIX D'OFFRE
B30: Prix indicatif demandé (M XOF) | C30: =D27 -> 601.51977
B31: Équivalent (k EUR) | C31: =C30*1000/$E$8 -> 917.01098
B32: Fourchette de négociation (M XOF) | C32: =TEXT(C27,"#,##0")&" — "&TEXT(E27,"#,##0")&" M XOF" -> 311 — 1,001 M XOF
B34: POINTS D'ATTENTION CLÉS POUR L'ACQUÉREUR
B35: • Écart entre CA déclaré dans les états financiers 2025 (244 M XOF) et CA réel facturé (752 M XOF) — risque de régularisation fiscale à provisionner.
B36: • Concentration clients : Bessac Afrique = ~32% du CA cumulé 2024-2025. Mitigation par contractualisation pluriannuelle.
B37: • Dépendance forte aux compétences clés du gérant et au portefeuille relationnel.
B38: • Pénalités fiscales budgétées 2026 (~11 M XOF) — provisions complémentaires possibles.
B39: • Croissance soutenue : +44% (2024→2025), prévisionnel 2026 à +127% selon plan de trésorerie (à valider en linéaire YTD).
B40: • Trésorerie nette positive au 31/12/2025 : +20,6 M XOF (cash) – 12,8 M XOF (dettes fiscales/sociales) = +7,8 M XOF.
B43: Légende couleurs : Bleu = hypothèses (modifiables) — Noir = formules — Vert = liens onglets — Jaune = sortie clé

Sheet Hypothèses
B2: HYPOTHÈSES DE VALORISATION
A4: Paramètres macro & financiers
B5: Taux EUR/XOF (peg fixe) | C5: 655.957 | F5: Source : peg fixe BCEAO
B6: Taux d'actualisation (WACC) | C6: 0.22 | F6: Risque pays Côte d'Ivoire + prime PME (15-25%)
B7: Taux de croissance terminal | C7: 0.03 | F7: Croissance long terme alignée PIB CI
B8: Taux d'IS effectif | C8: 0.25 | F8: Taux normal IS Côte d'Ivoire
B9: Inflation moyenne | C9: 0.03 | F9: Hypothèse de travail
A12: Hypothèses de croissance et de marge
B13: Année | C13: Croissance CA | D13: Marge EBITDA | E13: Marge nette
B14: 2026E | C14: 0.4 | D14: 0.25 | E14: 0.15
B15: 2027E | C15: 0.3 | D15: 0.27 | E15: 0.17
B16: 2028E | C16: 0.2 | D16: 0.27 | E16: 0.17
B17: 2029E | C17: 0.12 | D17: 0.26 | E17: 0.16
B18: 2030E | C18: 0.08 | D18: 0.25 | E18: 0.15
B19: Terminal | C19: 0.03 | D19: 0.25 | E19: 0.15
A22: Multiples retenus (PME services techniques Afrique de l'Ouest)
B23: Multiple | C23: Bas | D23: Central | E23: Haut | F23: Référence
B24: EV / EBITDA (trailing) | C24: 3 | D24: 4.5 | E24: 6 | F24: Comparables ingénierie / staff aug. - décote PME / risque pays
B25: EV / Sales (trailing 2025) | C25: 0.4 | D25: 0.55 | E25: 0.75 | F25: Services techniques B2B émergents
B26: EV / Sales (forward 2026) | C26: 0.3 | D26: 0.4 | E26: 0.55 | F26: Services techniques B2B émergents
A30: Normalisation de l'EBITDA pour la valorisation
B31: Marge EBITDA normalisée appliquée au CA réel | C31: 0.25 | F31: Hypothèse centrale (entre 20% et 30%)
B34: NOTES
B35: 1) WACC 22% : Risque pays CI (~7%), Risque taille PME (~6%), Spread illiquidité (~4%), Risque de régularisation fiscale (~3%) au-dessus d'un Rf base ~2%.
B36: 2) Le CA officiel des états financiers (244 M XOF en 2025) ne reflète pas l'activité économique réelle. La valorisation est basée sur le CA facturé réel.
B37: 3) Décote vente rapide : 10-30% selon urgence et largeur de la mise en concurrence avec acquéreurs.

Sheet CA réel
B2: CHIFFRE D'AFFAIRES RÉEL — DÉTAIL MENSUEL (XOF)
B4: Année | C4: Janv. | D4: Févr. | E4: Mars | F4: Avril | G4: Mai | H4: Juin | I4: Juil. | J4: Août | K4: Sept. | L4: Oct. | M4: Nov. | N4: Déc. | O4: Total
B5: 2024 | C5: 39153454 | D5: 26859726 | E5: 26474731 | F5: 42120676 | G5: 41717292 | H5: 38977303 | I5: 20858283 | J5: 47837895 | K5: 86684477 | L5: 51367833 | M5: 52271027 | N5: 48171828 | O5: =SUM(C5:N5) -> 522494525
B6: 2025 | C6: 30222312 | D6: 22085825 | E6: 64217234 | F6: 12055620 | G6: 63487499 | H6: 102825080 | I6: 78012832 | J6: 90233520 | K6: 28277344 | L6: 100358538 | M6: 20185156 | N6: 140491107 | O6: =SUM(C6:N6) -> 752452067
B7: 2026 YTD | C7: 52006866 | D7: 37734496 | E7: 138244635 | F7: 88801027 | G7: 50330690 | O7: =SUM(C7:N7) -> 367117714
B9: Δ YoY | O9: =O6/O5-1 -> 0.44011474
B11: Indicateurs
B12: Nombre de factures 2024 / 2025 / 2026 YTD | F12: 236 / 266 / 171
B13: Statuts (2024-2026) | F13: Comptabilisé : 666 — Annulé : 6 — Brouillon : 1
B14: Top 3 clients 2025 | F14: Bessac Afrique (32%), SPAC CI (25%), Seureca CI (9%)
B16: Annualisation 2026 (linéaire sur YTD) | F16: =O7/(124/365) -> 1.0806288e+09 | G16: (124 jours écoulés au 04/05)
B17: Budget 2026 (plan de trésorerie) | F17: 1710000000

Sheet P&L Normalisé
B2: COMPTE DE RÉSULTAT NORMALISÉ — En M XOF
B4: M XOF | C4: 2024A | D4: 2025A | E4: 2026E | F4: 2027E | G4: 2028E | H4: 2029E | I4: 2030E
B6: Chiffre d'affaires | C6: ='CA réel'!O5/1000000 -> 522.49452 | D6: ='CA réel'!O6/1000000 -> 752.45207 | E6: =D6*(1+Hypothèses!C14) -> 1053.4329 | F6: =E6*(1+Hypothèses!C15) -> 1369.4628 | G6: =F6*(1+Hypothèses!C16) -> 1643.3553 | H6: =G6*(1+Hypothèses!C17) -> 1840.558 | I6: =H6*(1+Hypothèses!C18) -> 1987.8026
B7: Croissance | D7: =D6/C6-1 -> 0.44011474 | E7: =Hypothèses!C14 -> 0.4 | F7: =Hypothèses!C15 -> 0.3 | G7: =Hypothèses!C16 -> 0.2 | H7: =Hypothèses!C17 -> 0.12 | I7: =Hypothèses!C18 -> 0.08
B9: Marge EBITDA (%) | C9: 0.2 | D9: 0.23 | E9: =Hypothèses!D14 -> 0.25 | F9: =Hypothèses!D15 -> 0.27 | G9: =Hypothèses!D16 -> 0.27 | H9: =Hypothèses!D17 -> 0.26 | I9: =Hypothèses!D18 -> 0.25
B10: EBITDA normalisé | C10: =C6*C9 -> 104.4989 | D10: =D6*D9 -> 173.06398 | E10: =E6*E9 -> 263.35822 | F10: =F6*F9 -> 369.75495 | G10: =G6*G9 -> 443.70593 | H10: =H6*H9 -> 478.54507 | I10: =I6*I9 -> 496.95065
B12: Dotations amortissements (~2% CA) | C12: =C6*0.02 -> 10.449891 | D12: =D6*0.02 -> 15.049041 | E12: =E6*0.02 -> 21.068658 | F12: =F6*0.02 -> 27.389255 | G12: =G6*0.02 -> 32.867106 | H12: =H6*0.02 -> 36.811159 | I12: =I6*0.02 -> 39.756052
B13: EBIT | C13: =C10-C12 -> 94.049014 | D13: =D10-D12 -> 158.01493 | E13: =E10-E12 -> 242.28957 | F13: =F10-F12 -> 342.36569 | G13: =G10-G12 -> 410.83883 | H13: =H10-H12 -> 441.73391 | I13: =I10-I12 -> 457.1946
B14: Impôts (-25%) | C14: =-C13*Hypothèses!$C$8 -> -23.512254 | D14: =-D13*Hypothèses!$C$8 -> -39.503734 | E14: =-E13*Hypothèses!$C$8 -> -60.572391 | F14: =-F13*Hypothèses!$C$8 -> -85.591423 | G14: =-G13*Hypothèses!$C$8 -> -102.70971 | H14: =-H13*Hypothèses!$C$8 -> -110.43348 | I14: =-I13*Hypothèses!$C$8 -> -114.29865
B15: NOPAT | C15: =C13+C14 -> 70.536761 | D15: =D13+D14 -> 118.5112 | E15: =E13+E14 -> 181.71717 | F15: =F13+F14 -> 256.77427 | G15: =G13+G14 -> 308.12912 | H15: =H13+H14 -> 331.30043 | I15: =I13+I14 -> 342.89595
B17: Note : EBITDA 2024-2025 estimé à partir du plan de trésorerie 2026 et de la marge déclarée en états financiers (corrigée du périmètre).

Sheet DCF
B2: VALORISATION PAR DCF — En M XOF
B4: M XOF | C4: 2026E | D4: 2027E | E4: 2028E | F4: 2029E | G4: 2030E
B5: Chiffre d'affaires | C5: ='P&L Normalisé'!E6 -> 1053.4329 | D5: ='P&L Normalisé'!F6 -> 1369.4628 | E5: ='P&L Normalisé'!G6 -> 1643.3553 | F5: ='P&L Normalisé'!H6 -> 1840.558 | G5: ='P&L Normalisé'!I6 -> 1987.8026
B6: EBITDA | C6: ='P&L Normalisé'!E10 -> 263.35822 | D6: ='P&L Normalisé'!F10 -> 369.75495 | E6: ='P&L Normalisé'!G10 -> 443.70593 | F6: ='P&L Normalisé'!H10 -> 478.54507 | G6: ='P&L Normalisé'!I10 -> 496.95065
B7: (-) Amortissements | C7: =-'P&L Normalisé'!E12 -> -21.068658 | D7: =-'P&L Normalisé'!F12 -> -27.389255 | E7: =-'P&L Normalisé'!G12 -> -32.867106 | F7: =-'P&L Normalisé'!H12 -> -36.811159 | G7: =-'P&L Normalisé'!I12 -> -39.756052
B8: EBIT | C8: =C6+C7 -> 242.28957 | D8: =D6+D7 -> 342.36569 | E8: =E6+E7 -> 410.83883 | F8: =F6+F7 -> 441.73391 | G8: =G6+G7 -> 457.1946
B9: (-) Impôts (25%) | C9: =-C8*Hypothèses!$C$8 -> -60.572391 | D9: =-D8*Hypothèses!$C$8 -> -85.591423 | E9: =-E8*Hypothèses!$C$8 -> -102.70971 | F9: =-F8*Hypothèses!$C$8 -> -110.43348 | G9: =-G8*Hypothèses!$C$8 -> -114.29865
B10: NOPAT | C10: =C8+C9 -> 181.71717 | D10: =D8+D9 -> 256.77427 | E10: =E8+E9 -> 308.12912 | F10: =F8+F9 -> 331.30043 | G10: =G8+G9 -> 342.89595
B11: (+) Amortissements | C11: =-C7 -> 21.068658 | D11: =-D7 -> 27.389255 | E11: =-E7 -> 32.867106 | F11: =-F7 -> 36.811159 | G11: =-G7 -> 39.756052
B12: (-) Capex (~3% CA) | C12: =-C5*0.03 -> -31.602987 | D12: =-D5*0.03 -> -41.083883 | E12: =-E5*0.03 -> -49.300659 | F12: =-F5*0.03 -> -55.216739 | G12: =-G5*0.03 -> -59.634078
B13: (-) Variation BFR (~10% Δ CA) | C13: =-(C5-'P&L Normalisé'!D6)*0.1 -> -30.098083 | D13: =-(D5-C5)*0.1 -> -31.602987 | E13: =-(E5-D5)*0.1 -> -27.389255 | F13: =-(F5-E5)*0.1 -> -19.720264 | G13: =-(G5-F5)*0.1 -> -14.724464
B14: Free Cash Flow (FCF) | C14: =C10+C11+C12+C13 -> 141.08476 | D14: =D10+D11+D12+D13 -> 211.47665 | E14: =E10+E11+E12+E13 -> 264.30631 | F14: =F10+F11+F12+F13 -> 293.17459 | G14: =G10+G11+G12+G13 -> 308.29346
B16: Période d'actualisation | C16: 0.65 | D16: =C16+1 -> 1.65 | E16: =D16+1 -> 2.65 | F16: =E16+1 -> 3.65 | G16: =F16+1 -> 4.65
B17: Facteur d'actualisation | C17: =1/(1+Hypothèses!$C$6)^C16 -> 0.87875156 | D17: =1/(1+Hypothèses!$C$6)^D16 -> 0.72028817 | E17: =1/(1+Hypothèses!$C$6)^E16 -> 0.59040014 | F17: =1/(1+Hypothèses!$C$6)^F16 -> 0.48393454 | G17: =1/(1+Hypothèses!$C$6)^G16 -> 0.39666765
B18: PV FCF | C18: =C14*C17 -> 123.97846 | D18: =D14*D17 -> 152.32413 | E18: =E14*E17 -> 156.04648 | F18: =F14*F17 -> 141.87731 | G18: =G14*G17 -> 122.29004
A20: Valeur terminale (Gordon)
B21: FCF terminal (FCF 2030 × (1+g)) | C21: =G14*(1+Hypothèses!C7) -> 317.54226
B22: Taux WACC - g | C22: =Hypothèses!C6-Hypothèses!C7 -> 0.19
B23: Valeur terminale (TV) | C23: =C21/C22 -> 1671.2751
B24: Facteur d'actualisation TV | C24: =G17 -> 0.39666765
B25: PV de la valeur terminale | C25: =C23*C24 -> 662.94076
A27: Valeur d'entreprise & équité
B28: Σ PV FCF (5 ans) | C28: =SUM(C18:G18) -> 696.51642
B29: PV Valeur Terminale | C29: =C25 -> 662.94076
B30: Valeur d'Entreprise (EV) | C30: =C28+C29 -> 1359.4572
B32: Bridge EV → Equity
B33: (+) Trésorerie au 31/12/2025 | C33: 20.6
B34: (-) Dettes financières | C34: 0
B35: (-) Dettes fiscales/sociales | C35: -12.8
B36: (-) Provision régularisation fiscale (estim.) | C36: -100
B37: Equity central (DCF) | C37: =C30+C33+C34+C35+C36 -> 1267.2572
B40: DCF — fourchette pour synthèse | C40: =C37*0.75 -> 950.44288 | D40: =C37 -> 1267.2572 | E40: =C37*1.25 -> 1584.0715 | F40: (±25%)
A42: Sensibilité Equity DCF (M XOF) — WACC × g terminal
B43: WACC \ g | C43: 0.02 | D43: 0.03 | E43: 0.04 | F43: 0.05
B44: 0.18 | C44: =C14/(1+0.18)^C16+D14/(1+0.18)^D16+E14/(1+0.18)^E16+F14/(1+0.18)^F16+G14/(1+0.18)^G16+(G14*(1+0.02)/(0.18-0.02))/(1+0.18)^G16+C33+C34+C35+C36 -> 1579.2387 | D44: =C14/(1+0.18)^C16+D14/(1+0.18)^D16+E14/(1+0.18)^E16+F14/(1+0.18)^F16+G14/(1+0.18)^G16+(G14*(1+0.03)/(0.18-0.03))/(1+0.18)^G16+C33+C34+C35+C36 -> 1649.4462 | E44: =C14/(1+0.18)^C16+D14/(1+0.18)^D16+E14/(1+0.18)^E16+F14/(1+0.18)^F16+G14/(1+0.18)^G16+(G14*(1+0.04)/(0.18-0.04))/(1+0.18)^G16+C33+C34+C35+C36 -> 1729.6834 | F44: =C14/(1+0.18)^C16+D14/(1+0.18)^D16+E14/(1+0.18)^E16+F14/(1+0.18)^F16+G14/(1+0.18)^G16+(G14*(1+0.05)/(0.18-0.05))/(1+0.18)^G16+C33+C34+C35+C36 -> 1822.2648
B45: 0.2 | C45: =C14/(1+0.2)^C16+D14/(1+0.2)^D16+E14/(1+0.2)^E16+F14/(1+0.2)^F16+G14/(1+0.2)^G16+(G14*(1+0.02)/(0.2-0.02))/(1+0.2)^G16+C33+C34+C35+C36 -> 1383.788 | D45: =C14/(1+0.2)^C16+D14/(1+0.2)^D16+E14/(1+0.2)^E16+F14/(1+0.2)^F16+G14/(1+0.2)^G16+(G14*(1+0.03)/(0.2-0.03))/(1+0.2)^G16+C33+C34+C35+C36 -> 1435.5762 | E45: =C14/(1+0.2)^C16+D14/(1+0.2)^D16+E14/(1+0.2)^E16+F14/(1+0.2)^F16+G14/(1+0.2)^G16+(G14*(1+0.04)/(0.2-0.04))/(1+0.2)^G16+C33+C34+C35+C36 -> 1493.838 | F45: =C14/(1+0.2)^C16+D14/(1+0.2)^D16+E14/(1+0.2)^E16+F14/(1+0.2)^F16+G14/(1+0.2)^G16+(G14*(1+0.05)/(0.2-0.05))/(1+0.2)^G16+C33+C34+C35+C36 -> 1559.8681
B46: 0.22 | C46: =C14/(1+0.22)^C16+D14/(1+0.22)^D16+E14/(1+0.22)^E16+F14/(1+0.22)^F16+G14/(1+0.22)^G16+(G14*(1+0.02)/(0.22-0.02))/(1+0.22)^G16+C33+C34+C35+C36 -> 1227.9956 | D46: =C14/(1+0.22)^C16+D14/(1+0.22)^D16+E14/(1+0.22)^E16+F14/(1+0.22)^F16+G14/(1+0.22)^G16+(G14*(1+0.03)/(0.22-0.03))/(1+0.22)^G16+C33+C34+C35+C36 -> 1267.2572 | E46: =C14/(1+0.22)^C16+D14/(1+0.22)^D16+E14/(1+0.22)^E16+F14/(1+0.22)^F16+G14/(1+0.22)^G16+(G14*(1+0.04)/(0.22-0.04))/(1+0.22)^G16+C33+C34+C35+C36 -> 1310.8811 | F46: =C14/(1+0.22)^C16+D14/(1+0.22)^D16+E14/(1+0.22)^E16+F14/(1+0.22)^F16+G14/(1+0.22)^G16+(G14*(1+0.05)/(0.22-0.05))/(1+0.22)^G16+C33+C34+C35+C36 -> 1359.6373
B47: 0.24 | C47: =C14/(1+0.24)^C16+D14/(1+0.24)^D16+E14/(1+0.24)^E16+F14/(1+0.24)^F16+G14/(1+0.24)^G16+(G14*(1+0.02)/(0.24-0.02))/(1+0.24)^G16+C33+C34+C35+C36 -> 1101.0095 | D47: =C14/(1+0.24)^C16+D14/(1+0.24)^D16+E14/(1+0.24)^E16+F14/(1+0.24)^F16+G14/(1+0.24)^G16+(G14*(1+0.03)/(0.24-0.03))/(1+0.24)^G16+C33+C34+C35+C36 -> 1131.4417 | E47: =C14/(1+0.24)^C16+D14/(1+0.24)^D16+E14/(1+0.24)^E16+F14/(1+0.24)^F16+G14/(1+0.24)^G16+(G14*(1+0.04)/(0.24-0.04))/(1+0.24)^G16+C33+C34+C35+C36 -> 1164.9171 | F47: =C14/(1+0.24)^C16+D14/(1+0.24)^D16+E14/(1+0.24)^E16+F14/(1+0.24)^F16+G14/(1+0.24)^G16+(G14*(1+0.05)/(0.24-0.05))/(1+0.24)^G16+C33+C34+C35+C36 -> 1201.9163
B48: 0.26 | C48: =C14/(1+0.26)^C16+D14/(1+0.26)^D16+E14/(1+0.26)^E16+F14/(1+0.26)^F16+G14/(1+0.26)^G16+(G14*(1+0.02)/(0.26-0.02))/(1+0.26)^G16+C33+C34+C35+C36 -> 995.59779 | D48: =C14/(1+0.26)^C16+D14/(1+0.26)^D16+E14/(1+0.26)^E16+F14/(1+0.26)^F16+G14/(1+0.26)^G16+(G14*(1+0.03)/(0.26-0.03))/(1+0.26)^G16+C33+C34+C35+C36 -> 1019.6233 | E48: =C14/(1+0.26)^C16+D14/(1+0.26)^D16+E14/(1+0.26)^E16+F14/(1+0.26)^F16+G14/(1+0.26)^G16+(G14*(1+0.04)/(0.26-0.04))/(1+0.26)^G16+C33+C34+C35+C36 -> 1045.833 | F48: =C14/(1+0.26)^C16+D14/(1+0.26)^D16+E14/(1+0.26)^E16+F14/(1+0.26)^F16+G14/(1+0.26)^G16+(G14*(1+0.05)/(0.26-0.05))/(1+0.26)^G16+C33+C34+C35+C36 -> 1074.5388

Sheet Multiples
B2: VALORISATION PAR MULTIPLES — En M XOF
A4: Multiple EV/EBITDA — base CA réel 2025 normalisé
B5: Indicateur | C5: Bas | D5: Central | E5: Haut
B6: CA 2025 réel (M XOF) | C6: ='P&L Normalisé'!D6 -> 752.45207 | D6: ='P&L Normalisé'!D6 -> 752.45207 | E6: ='P&L Normalisé'!D6 -> 752.45207
B7: Marge EBITDA normalisée | C7: 0.2 | D7: 0.25 | E7: 0.3
B8: EBITDA normalisé | C8: =C6*C7 -> 150.49041 | D8: =D6*D7 -> 188.11302 | E8: =E6*E7 -> 225.73562
B9: Multiple EV/EBITDA | C9: =Hypothèses!C24 -> 3 | D9: =Hypothèses!D24 -> 4.5 | E9: =Hypothèses!E24 -> 6
B10: Valeur d'Entreprise (EV) | C10: =C8*C9 -> 451.47124 | D10: =D8*D9 -> 846.50858 | E10: =E8*E9 -> 1354.4137
B12: (+) Trésorerie | C12: 20.6 | D12: 20.6 | E12: 20.6
B13: (-) Dettes financières et fiscales | C13: -12.8 | D13: -12.8 | E13: -12.8
B14: (-) Provision régularisation fiscale | C14: -150 | D14: -100 | E14: -50
B15: Equity (M XOF) | C15: =C10+C12+C13+C14 -> 309.27124 | D15: =D10+D12+D13+D14 -> 754.30858 | E15: =E10+E12+E13+E14 -> 1312.2137
B20: Equity multiple EBITDA — pour synthèse | C20: =C15 -> 309.27124 | D20: =D15 -> 754.30858 | E20: =E15 -> 1312.2137
A22: Multiple EV/Sales — base CA 2025 réel
B23: CA 2025 réel | C23: ='P&L Normalisé'!D6 -> 752.45207 | D23: ='P&L Normalisé'!D6 -> 752.45207 | E23: ='P&L Normalisé'!D6 -> 752.45207
B24: Multiple EV/Sales | C24: =Hypothèses!C25 -> 0.4 | D24: =Hypothèses!D25 -> 0.55 | E24: =Hypothèses!E25 -> 0.75
B25: Valeur d'Entreprise | C25: =C23*C24 -> 300.98083 | D25: =D23*D24 -> 413.84864 | E25: =E23*E24 -> 564.33905
B26: (+) Trésorerie - (-) Dettes - Prov. | C26: =C12+C13+C14 -> -142.2 | D26: =D12+D13+D14 -> -92.2 | E26: =E12+E13+E14 -> -42.2
B27: Equity (M XOF) | C27: =C25+C26 -> 158.78083 | D27: =D25+D26 -> 321.64864 | E27: =E25+E26 -> 522.13905
B29: Equity multiple Sales — pour synthèse | C29: =C27 -> 158.78083 | D29: =D27 -> 321.64864 | E29: =E27 -> 522.13905
A31: Vérification — Multiple EV/Sales forward (CA 2026E)
B32: CA 2026E | C32: ='P&L Normalisé'!E6 -> 1053.4329
B33: Multiple EV/Sales forward | C33: =Hypothèses!C26 -> 0.3 | D33: =Hypothèses!D26 -> 0.4 | E33: =Hypothèses!E26 -> 0.55
B34: EV forward | C34: =$C$32*C33 -> 316.02987 | D34: =$C$32*D33 -> 421.37316 | E34: =$C$32*E33 -> 579.38809

Sheet Patrimoniale
B2: MÉTHODE PATRIMONIALE — Actif Net Réévalué (M XOF)
B4: Poste | C4: Bilan 31/12/25 | D4: Réévaluation | E4: ANR
B5: ACTIF
B6: Immobilisations incorporelles | C6: 9.015 | D6: 0 | E6: =C6+D6 -> 9.015
B7: Immobilisations corporelles | C7: 13.182 | D7: 0 | E7: =C7+D7 -> 13.182
B8: Immobilisations financières | C8: 3.2 | D8: 0 | E8: =C8+D8 -> 3.2
B9: Créances clients | C9: 26.109 | D9: -2.611 | E9: =C9+D9 -> 23.498
B10: Trésorerie | C10: 20.595 | D10: 0 | E10: =C10+D10 -> 20.595
B11: TOTAL ACTIF RÉÉVALUÉ | C11: =SUM(C6:C10) -> 72.101 | D11: =SUM(D6:D10) -> -2.611 | E11: =SUM(E6:E10) -> 69.49
B13: DETTES (à déduire)
B14: Dettes fiscales et sociales | C14: 12.796 | D14: 0 | E14: =C14+D14 -> 12.796
B15: Dettes fournisseurs | C15: 0 | D15: 0 | E15: =C15+D15 -> 0
B16: Provision régularisation fiscale (estim.) | C16: 100 | D16: 0 | E16: =C16+D16 -> 100
B17: TOTAL DETTES | C17: =SUM(C14:C16) -> 112.796 | D17: =SUM(D14:D16) -> 0 | E17: =SUM(E14:E16) -> 112.796
B18: (+) Goodwill (clientèle, savoir-faire) | C18: 100
B19: ACTIF NET RÉÉVALUÉ + GW | E19: =E11-E17+C18 -> 56.694
B20: Patrimoniale — fourchette pour synthèse | C20: =E19*0.6 -> 34.0164 | D20: =E19 -> 56.694 | E20: =E19*1.4 -> 79.3716
B22: Note : la méthode patrimoniale est peu adaptée à un cabinet de services dont la valeur réside dans le portefeuille client et le savoir-faire (incorporels non-comptabilisés). Elle constitue ici un plancher de référence.

Sheet Bilan résumé
B2: BILAN AT225 — Synthèse exercice clos 31/12/2025 (XOF)
B4: ACTIF (NET) | C4: 31/12/2025 | D4: 31/12/2024
B5: Immobilisations incorporelles (logiciels) | C5: 9015464 | D5: 13455917
B6: Immobilisations corporelles | C6: 13181973 | D6: 16573748
B7: dont matériel mobilier | C7: 5610973 | D7: 5273748
B8: dont matériel de transport | C8: 7571000 | D8: 11300000
B9: Immobilisations financières | C9: 3200000 | D9: 0
B10: Total actif immobilisé | C10: 25397437 | D10: 30029665
B11: Créances clients | C11: 26108540 | D11: 0
B12: Total actif circulant | C12: 26108540 | D12: 0
B13: Trésorerie active (banques, caisse) | C13: 20594958 | D13: 6285553
B14: TOTAL ACTIF | C14: 72100935 | D14: 36315218
B17: PASSIF | C17: 31/12/2025 | D17: 31/12/2024
B18: Capital social | C18: 1000000 | D18: 1000000
B19: Report à nouveau | C19: -4100000 | D19: 0
B20: Résultat net de l'exercice | C20: 62405336 | D20: -15300000
B21: Total capitaux propres | C21: 59305336 | D21: -14300000
B22: Dettes fiscales et sociales | C22: 12795599 | D22: 7037063
B23: Dettes fournisseurs | C23: 0 | D23: 19896828
B24: Autres dettes | C24: 0 | D24: 23681327
B25: Total passif circulant | C25: 12795599 | D25: 50615218
B26: Trésorerie passive | C26: 0 | D26: 0
B27: TOTAL PASSIF | C27: 72100935 | D27: 36315218
B30: Source : États financiers provisoires AT225 au 31/12/2025
B32: ALERTE : Comparaison CA déclaré vs CA facturé
B33: CA déclaré (états financiers 2025) | C33: 243879644
B34: CA facturé réel (fichier facturation 2025) | C34: 752452067
B35: Écart | C35: =C34-C33 -> 508572423
B36: Écart en % du CA réel | C36: =C35/C34 -> 0.6758868
B38: Cette différence représente une exposition de régularisation fiscale (impôts/IS) dont le buyer demandera couverture par garantie de passif.
